README.rst
setup.py
_mypy_easy_addoption_plugin/__init__.py
_mypy_easy_addoption_plugin/plugin.py
_pytest_easy_addoption/__init__.py
_pytest_easy_addoption/config_holder.py
_pytest_easy_addoption/plugin.py
easy_addoption/__init__.py
easy_addoption/addoption.py
easy_addoption/exceptions.py
easy_addoption/missing.py
easy_addoption/option.py
easy_addoption/types.py
pytest_easy_addoption.egg-info/PKG-INFO
pytest_easy_addoption.egg-info/SOURCES.txt
pytest_easy_addoption.egg-info/dependency_links.txt
pytest_easy_addoption.egg-info/entry_points.txt
pytest_easy_addoption.egg-info/requires.txt
pytest_easy_addoption.egg-info/top_level.txt